<?xml version="1.0" encoding="UTF-8"?>
<patterns>
    <pattern id="1" value="0">
        <names>
            <name lang="jp">パターン1</name>
            <name lang="en">Pattern 1</name>
        </names>
        <funcgroups>
            <funcgroup id="5" />
        </funcgroups>
    </pattern>
    <pattern id="2" value="1">
        <names>
            <name lang="jp">パターン2</name>
            <name lang="en">Pattern 2</name>
        </names>
        <funcgroups>
        </funcgroups>
    </pattern>
    <pattern id="3" value="2">
        <names>
            <name lang="jp">パターン3</name>
            <name lang="en">Pattern 3</name>
        </names>
        <funcgroups>
            <funcgroup id="9" />
        </funcgroups>
    </pattern>
    <pattern id="4" value="3">
        <names>
            <name lang="jp">パターン4</name>
            <name lang="en">Pattern 4</name>
        </names>
        <funcgroups>
        </funcgroups>
    </pattern>
    <pattern id="5" value="4">
        <names>
            <name lang="jp">パターン5</name>
            <name lang="en">Pattern 5</name>
        </names>
        <funcgroups>
        </funcgroups>
    </pattern>
</patterns>
